jackett_indexerarr/__init__.py
jackett_indexerarr/cli.py
jackett_indexerarr/utils.py
jackett_indexerarr-0.16.1.dist-info/METADATA
jackett_indexerarr-0.16.1.dist-info/entry_points.txt
jackett_indexerarr-0.16.1.dist-info/WHEEL
jackett_indexerarr-0.16.1.dist-info/LICENSE
jackett_indexerarr-0.16.1.dist-info/RECORD
