Metadata-Version: 2.1
Name: jackett-indexerarr
Version: 0.16.1
Summary: 
Home-page: https://github.com/dmzoneill/jackett-indexerarr
Author: David O Neill
Author-email: dmz.oneill@gmail.com
Requires-Python: >=3.8,<4.0
Classifier: Programming Language :: Python :: 3
Classifier: Programming Language :: Python :: 3.8
Classifier: Programming Language :: Python :: 3.9
Classifier: Programming Language :: Python :: 3.10
Classifier: Programming Language :: Python :: 3.11
Requires-Dist: requests
Requires-Dist: typer
Project-URL: Repository, https://github.com/dmzoneill/jackett-indexerarr
